MANIFEST.in
README.rst
setup.py
tox.ini
django_websettings.egg-info/PKG-INFO
django_websettings.egg-info/SOURCES.txt
django_websettings.egg-info/dependency_links.txt
django_websettings.egg-info/not-zip-safe
django_websettings.egg-info/requires.txt
django_websettings.egg-info/top_level.txt
websettings/__init__.py
websettings/authentication.py
websettings/base.py
websettings/forms.py
websettings/models.py
websettings/testing.py
websettings/urls.py
websettings/views.py
websettings/backends/__init__.py
websettings/backends/db.py
websettings/management/__init__.py
websettings/management/commands/__init__.py
websettings/management/commands/print_websettings.py
websettings/static/websettings/css/bootstrap.min.css
websettings/templates/websettings/base.html
websettings/templates/websettings/edit.html
websettings/templates/websettings/list.html
websettings/tests/__init__.py
websettings/tests/settingstore.py
websettings/tests/tests.py