Metadata-Version: 1.0
Name: django-websettings
Version: 0.1
Summary: Django application to provide a web interface to set a yet another django's settings
Home-page: https://github.com/hirokiky/django-websettings
Author: Hiroki KIYOHARA
Author-email: hirokiky@gmail.com
License: UNKNOWN
Keywords: web wsgi django
Platform: UNKNOWN
Classifier: Development Status :: 4 - Beta
Classifier: License :: OSI Approved :: MIT License
Classifier: Environment :: Web Environment
Classifier: Programming Language :: Python :: 2.7
Classifier: Programming Language :: Python :: 3.2
Classifier: Programming Language :: Python :: 3.3
Classifier: Framework :: Django
Classifier: Topic :: Internet :: WWW/HTTP
Classifier: Topic :: Internet :: WWW/HTTP :: WSGI :: Application
